fileglancer_central/__init__.py
fileglancer_central/alembic.ini
fileglancer_central/app.py
fileglancer_central/database.py
fileglancer_central/issues.py
fileglancer_central/model.py
fileglancer_central/proxy_context.py
fileglancer_central/settings.py
fileglancer_central/stamp_db.py
fileglancer_central/utils.py
fileglancer_central/alembic/env.py
fileglancer_central/alembic/script.py.mako
fileglancer_central/alembic/__pycache__/env.cpython-312.pyc
fileglancer_central/alembic/versions/4bd357f37922_add_external_buckets_table.py
fileglancer_central/alembic/versions/711feaa741bb_add_table_name_column_to_lastrefreshdb.py
fileglancer_central/alembic/versions/9783bd3941f1_initial_schema.py
fileglancer_central/alembic/versions/__pycache__/4bd357f37922_add_external_buckets_table.cpython-312.pyc
fileglancer_central/alembic/versions/__pycache__/711feaa741bb_add_table_name_column_to_lastrefreshdb.cpython-312.pyc
fileglancer_central/alembic/versions/__pycache__/9783bd3941f1_initial_schema.cpython-312.pyc
fileglancer_central-1.0.0.dist-info/licenses/LICENSE
fileglancer_central-1.0.0.dist-info/METADATA
fileglancer_central-1.0.0.dist-info/WHEEL
fileglancer_central-1.0.0.dist-info/top_level.txt
fileglancer_central-1.0.0.dist-info/RECORD
