Metadata-Version: 2.4
Name: fileglancer-central
Version: 1.0.0
Author-email: Allison Truhlar <truhlara@janelia.hhmi.org>, Jody Clements <clementsj@janelia.hhmi.org>, Cristian Goina <goinac@janelia.hhmi.org>, Konrad Rokicki <rokickik@janelia.hhmi.org>
License: BSD 3-Clause License
Classifier: Programming Language :: Python :: 3
Classifier: Programming Language :: Python :: 3.12
Classifier: License :: OSI Approved :: BSD License
Classifier: Operating System :: OS Independent
Requires-Python: >=3.12
License-File: LICENSE
Requires-Dist: fastapi>=0.115
Requires-Dist: uvicorn>=0.34
Requires-Dist: sqlalchemy>=2.0
Requires-Dist: aiosqlite>=0.21.0
Requires-Dist: alembic>=1.13.0
Requires-Dist: pandas>=2.2.3
Requires-Dist: pydantic>=2.10
Requires-Dist: pydantic-settings>=2.8
Requires-Dist: pydantic-settings[yaml]
Requires-Dist: loguru>=0.7.2
Requires-Dist: atlassian-python-api>=3.41
Requires-Dist: lxml>=5.3.1
Requires-Dist: x2s3>=0.9.1
Requires-Dist: psycopg2-binary<3,>=2.9.9
Requires-Dist: cachetools>=5.0.0
Provides-Extra: test
Requires-Dist: pytest; extra == "test"
Requires-Dist: pytest-cov; extra == "test"
Requires-Dist: pytest-html; extra == "test"
Requires-Dist: httpx>=0.28; extra == "test"
Provides-Extra: release
Requires-Dist: build; extra == "release"
Requires-Dist: twine; extra == "release"
Dynamic: license-file
